{
  "firstLayout": "",
  "gdVersion": {
    "build": 99,
    "major": 4,
    "minor": 0,
    "revision": 0
  },
  "properties": {
    "adaptGameResolutionAtRuntime": true,
    "folderProject": false,
    "orientation": "landscape",
    "packageName": "com.example.gamename",
    "pixelsRounding": false,
    "projectUuid": "066f45b2-8b3b-421d-8288-7d3de449ba20",
    "scaleMode": "linear",
    "sizeOnStartupMode": "adaptWidth",
    "templateSlug": "",
    "useExternalSourceFiles": false,
    "version": "1.0.0",
    "name": "platform-game",
    "description": "",
    "author": "",
    "windowWidth": 1280,
    "windowHeight": 720,
    "latestCompilationDirectory": "",
    "maxFPS": 60,
    "minFPS": 20,
    "verticalSync": false,
    "platformSpecificAssets": {},
    "loadingScreen": {
      "backgroundColor": 0,
      "backgroundFadeInDuration": 0.2,
      "backgroundImageResourceName": "",
      "gdevelopLogoStyle": "light",
      "logoAndProgressFadeInDuration": 0.2,
      "logoAndProgressLogoFadeInDelay": 0.2,
      "minDuration": 1.5,
      "progressBarColor": 16777215,
      "progressBarHeight": 20,
      "progressBarMaxWidth": 200,
      "progressBarMinWidth": 40,
      "progressBarWidthPercent": 30,
      "showGDevelopSplash": true,
      "showProgressBar": true
    },
    "authorIds": [],
    "categories": [],
    "playableDevices": [],
    "extensionProperties": [],
    "platforms": [
      {
        "name": "GDevelop JS platform"
      }
    ],
    "currentPlatform": "GDevelop JS platform"
  },
  "resources": {
    "resources": [
      {
        "alwaysLoaded": false,
        "file": "img/p1_stand.png",
        "kind": "image",
        "metadata": "",
        "name": "img/p1_stand.png",
        "smoothed": true,
        "userAdded": true
      },
      {
        "alwaysLoaded": false,
        "file": "img/grassHalfMid.png",
        "kind": "image",
        "metadata": "",
        "name": "img/grassHalfMid.png",
        "smoothed": true,
        "userAdded": true
      },
      {
        "alwaysLoaded": false,
        "file": "img/Grass.png",
        "kind": "image",
        "metadata": "",
        "name": "img/Grass.png",
        "smoothed": true,
        "userAdded": true
      },
      {
        "alwaysLoaded": false,
        "file": "img/p1_jump.png",
        "kind": "image",
        "metadata": "",
        "name": "img/p1_jump.png",
        "smoothed": true,
        "userAdded": true
      },
      {
        "alwaysLoaded": false,
        "file": "img/p1_walk07.png",
        "kind": "image",
        "metadata": "",
        "name": "img/p1_walk07.png",
        "smoothed": true,
        "userAdded": true
      },
      {
        "alwaysLoaded": false,
        "file": "img/p1_walk06.png",
        "kind": "image",
        "metadata": "",
        "name": "img/p1_walk06.png",
        "smoothed": true,
        "userAdded": true
      },
      {
        "alwaysLoaded": false,
        "file": "img/p1_walk05.png",
        "kind": "image",
        "metadata": "",
        "name": "img/p1_walk05.png",
        "smoothed": true,
        "userAdded": false
      },
      {
        "alwaysLoaded": false,
        "file": "img/p1_walk04.png",
        "kind": "image",
        "metadata": "",
        "name": "img/p1_walk04.png",
        "smoothed": true,
        "userAdded": false
      },
      {
        "alwaysLoaded": false,
        "file": "img/p1_walk03.png",
        "kind": "image",
        "metadata": "",
        "name": "img/p1_walk03.png",
        "smoothed": true,
        "userAdded": true
      },
      {
        "alwaysLoaded": false,
        "file": "img/bridgeLogs.png",
        "kind": "image",
        "metadata": "",
        "name": "img/bridgeLogs.png",
        "smoothed": true,
        "userAdded": true
      },
      {
        "alwaysLoaded": false,
        "file": "img/bush.png",
        "kind": "image",
        "metadata": "",
        "name": "img/bush.png",
        "smoothed": true,
        "userAdded": true
      },
      {
        "alwaysLoaded": false,
        "file": "img/cloud2.png",
        "kind": "image",
        "metadata": "",
        "name": "img/cloud2.png",
        "smoothed": true,
        "userAdded": true
      },
      {
        "alwaysLoaded": false,
        "file": "img/coinGold.png",
        "kind": "image",
        "metadata": "",
        "name": "img/coinGold.png",
        "smoothed": true,
        "userAdded": true
      },
      {
        "file": "sounds/coin.mp3",
        "kind": "audio",
        "metadata": "",
        "name": "sounds/coin.mp3",
        "preloadAsMusic": false,
        "preloadAsSound": false,
        "preloadInCache": false,
        "userAdded": true
      },
      {
        "file": "fonts/Bimbo_JVE.ttf",
        "kind": "font",
        "metadata": "",
        "name": "fonts/Bimbo_JVE.ttf",
        "userAdded": true
      },
      {
        "alwaysLoaded": false,
        "file": "img/slimeWalk1.png",
        "kind": "image",
        "metadata": "",
        "name": "img/slimeWalk1.png",
        "smoothed": true,
        "userAdded": true
      },
      {
        "alwaysLoaded": false,
        "file": "img/slimeWalk2.png",
        "kind": "image",
        "metadata": "",
        "name": "img/slimeWalk2.png",
        "smoothed": true,
        "userAdded": true
      },
      {
        "alwaysLoaded": false,
        "file": "img/Left.png",
        "kind": "image",
        "metadata": "",
        "name": "img/Left.png",
        "smoothed": true,
        "userAdded": true
      },
      {
        "alwaysLoaded": false,
        "file": "img/Right.png",
        "kind": "image",
        "metadata": "",
        "name": "img/Right.png",
        "smoothed": true,
        "userAdded": true
      }
    ],
    "resourceFolders": []
  },
  "objects": [],
  "objectsGroups": [],
  "variables": [],
  "layouts": [
    {
      "b": 212,
      "disableInputWhenNotFocused": true,
      "mangledName": "New_32scene",
      "name": "New scene",
      "r": 146,
      "standardSortMethod": true,
      "stopSoundsOnStartup": true,
      "title": "",
      "v": 197,
      "uiSettings": {
        "grid": false,
        "gridType": "rectangular",
        "gridWidth": 32,
        "gridHeight": 32,
        "gridOffsetX": 0,
        "gridOffsetY": 0,
        "gridColor": 10401023,
        "gridAlpha": 0.8,
        "snap": false,
        "zoomFactor": 0.546875,
        "windowMask": false
      },
      "objectsGroups": [],
      "variables": [
        {
          "folded": true,
          "name": "Score",
          "type": "number",
          "value": 0
        }
      ],
      "instances": [
        {
          "angle": 0,
          "customSize": false,
          "height": 0,
          "layer": "",
          "name": "Player",
          "persistentUuid": "cead4686-9b2e-42d1-b80b-70c1a4ff8a96",
          "width": 0,
          "x": 17,
          "y": 599,
          "zOrder": 1,
          "numberProperties": [],
          "stringProperties": [],
          "initialVariables": []
        },
        {
          "angle": 0,
          "customSize": true,
          "height": 32,
          "layer": "",
          "name": "BottomGrassPlatform",
          "persistentUuid": "89bed9c0-c3b9-4a0c-b4f0-2d5d2eb3b245",
          "width": 548,
          "x": -3,
          "y": 690,
          "zOrder": 2,
          "numberProperties": [],
          "stringProperties": [],
          "initialVariables": []
        },
        {
          "angle": 0,
          "customSize": true,
          "height": 32,
          "layer": "",
          "name": "GrassPlatform",
          "persistentUuid": "cea6d65f-33f5-4d90-8199-fffdf995630d",
          "width": 714,
          "x": 564,
          "y": 562,
          "zOrder": 3,
          "numberProperties": [],
          "stringProperties": [],
          "initialVariables": []
        },
        {
          "angle": 0,
          "customSize": true,
          "height": 32,
          "layer": "",
          "name": "GrassPlatform",
          "persistentUuid": "7e987715-9ff3-450c-bba9-bd6abfae8bc7",
          "width": 423,
          "x": 857,
          "y": 318,
          "zOrder": 4,
          "numberProperties": [],
          "stringProperties": [],
          "initialVariables": []
        },
        {
          "angle": 0,
          "customSize": false,
          "height": 0,
          "layer": "",
          "name": "SmallBridge",
          "persistentUuid": "40bd27e8-1248-49f6-8465-af0534111836",
          "width": 0,
          "x": 766,
          "y": 447,
          "zOrder": 5,
          "numberProperties": [],
          "stringProperties": [],
          "initialVariables": []
        },
        {
          "angle": 0,
          "customSize": true,
          "height": 101,
          "layer": "",
          "name": "Bush",
          "persistentUuid": "05b37aa0-effe-4231-9a82-2927afc05f23",
          "width": 112,
          "x": 146,
          "y": 590,
          "zOrder": -2,
          "numberProperties": [],
          "stringProperties": [],
          "initialVariables": []
        },
        {
          "angle": 0,
          "customSize": false,
          "height": 0,
          "layer": "",
          "name": "Bush",
          "persistentUuid": "530973cb-8f00-4a4c-9f85-58cf22362278",
          "width": 0,
          "x": 348,
          "y": 621,
          "zOrder": -2,
          "numberProperties": [],
          "stringProperties": [],
          "initialVariables": []
        },
        {
          "angle": 0,
          "customSize": false,
          "height": 0,
          "layer": "",
          "name": "Bush",
          "persistentUuid": "a90c99bb-fb43-4bc7-82b8-989a99161580",
          "width": 0,
          "x": 953,
          "y": 251,
          "zOrder": -2,
          "numberProperties": [],
          "stringProperties": [],
          "initialVariables": []
        },
        {
          "angle": 0,
          "customSize": false,
          "height": 0,
          "layer": "",
          "name": "Cloud",
          "persistentUuid": "b8401409-5d4e-4c4d-a552-64a0bda42ca8",
          "width": 0,
          "x": 146,
          "y": 486,
          "zOrder": -2,
          "numberProperties": [],
          "stringProperties": [],
          "initialVariables": []
        },
        {
          "angle": 0,
          "customSize": false,
          "height": 0,
          "layer": "",
          "name": "Cloud",
          "persistentUuid": "b6fd403a-064d-4d00-87a5-faf6de1961eb",
          "width": 0,
          "x": -43,
          "y": -12,
          "zOrder": -2,
          "numberProperties": [],
          "stringProperties": [],
          "initialVariables": []
        },
        {
          "angle": 0,
          "customSize": false,
          "height": 0,
          "layer": "",
          "name": "Cloud",
          "persistentUuid": "c6630917-98ef-4e92-aa1d-47de37b797a0",
          "width": 0,
          "x": 434,
          "y": 231,
          "zOrder": -2,
          "numberProperties": [],
          "stringProperties": [],
          "initialVariables": []
        },
        {
          "angle": 0,
          "customSize": false,
          "height": 0,
          "layer": "",
          "name": "Cloud",
          "persistentUuid": "6765f291-68f0-4e44-96a6-188e97b8af93",
          "width": 0,
          "x": 871,
          "y": 43,
          "zOrder": -2,
          "numberProperties": [],
          "stringProperties": [],
          "initialVariables": []
        },
        {
          "angle": 0,
          "customSize": false,
          "height": 0,
          "layer": "",
          "name": "Coin",
          "persistentUuid": "b6e2e78d-5b9a-490b-a240-5542cc5b12eb",
          "width": 0,
          "x": 1200,
          "y": 448,
          "zOrder": 6,
          "numberProperties": [],
          "stringProperties": [],
          "initialVariables": []
        },
        {
          "angle": 0,
          "customSize": false,
          "height": 0,
          "layer": "",
          "name": "Coin",
          "persistentUuid": "da51718b-2e14-4915-9727-c5b24bf77baa",
          "width": 0,
          "x": 221,
          "y": 613,
          "zOrder": 6,
          "numberProperties": [],
          "stringProperties": [],
          "initialVariables": []
        },
        {
          "angle": 0,
          "customSize": false,
          "height": 0,
          "layer": "",
          "name": "Coin",
          "persistentUuid": "4532d6ac-92a2-4284-84cd-24490a75986a",
          "width": 0,
          "x": 455,
          "y": 556,
          "zOrder": 6,
          "numberProperties": [],
          "stringProperties": [],
          "initialVariables": []
        },
        {
          "angle": 0,
          "customSize": false,
          "height": 0,
          "layer": "",
          "name": "Coin",
          "persistentUuid": "d4d4f7c7-e984-4f0d-b654-e4cba86702d8",
          "width": 0,
          "x": 782,
          "y": 371,
          "zOrder": 6,
          "numberProperties": [],
          "stringProperties": [],
          "initialVariables": []
        },
        {
          "angle": 0,
          "customSize": false,
          "height": 0,
          "layer": "",
          "name": "Coin",
          "persistentUuid": "39c94106-7875-4582-bc3e-83835f1be397",
          "width": 0,
          "x": 937,
          "y": 117,
          "zOrder": 6,
          "numberProperties": [],
          "stringProperties": [],
          "initialVariables": []
        },
        {
          "angle": 0,
          "customSize": false,
          "height": 0,
          "layer": "UI",
          "name": "Score",
          "persistentUuid": "9b07c770-03b5-4bf5-83fb-6b3c46f0e49a",
          "width": 0,
          "x": 64,
          "y": 63,
          "zOrder": 7,
          "numberProperties": [],
          "stringProperties": [],
          "initialVariables": []
        },
        {
          "angle": 0,
          "customSize": false,
          "height": 0,
          "layer": "",
          "name": "left",
          "persistentUuid": "bf79a785-51e9-4109-a428-9b9fb60d87e4",
          "width": 0,
          "x": 547,
          "y": 665,
          "zOrder": 8,
          "numberProperties": [],
          "stringProperties": [],
          "initialVariables": []
        },
        {
          "angle": 0,
          "customSize": false,
          "height": 0,
          "layer": "",
          "name": "right",
          "persistentUuid": "dbd71a8c-bc94-4eb8-a4b6-6e4a68feee81",
          "width": 0,
          "x": -1,
          "y": 656,
          "zOrder": 9,
          "numberProperties": [],
          "stringProperties": [],
          "initialVariables": []
        },
        {
          "angle": 0,
          "customSize": false,
          "height": 0,
          "layer": "",
          "name": "Slime",
          "persistentUuid": "3529fe0d-c757-4094-9d8d-8c6bdb20ffdb",
          "width": 0,
          "x": 481,
          "y": 663,
          "zOrder": 10,
          "numberProperties": [],
          "stringProperties": [],
          "initialVariables": []
        },
        {
          "angle": 0,
          "customSize": false,
          "height": 0,
          "layer": "",
          "name": "Slime",
          "persistentUuid": "3be0cba5-88b4-4d13-a531-07ef990cd746",
          "width": 0,
          "x": 1183,
          "y": 537,
          "zOrder": 10,
          "numberProperties": [],
          "stringProperties": [],
          "initialVariables": []
        },
        {
          "angle": 0,
          "customSize": false,
          "height": 0,
          "layer": "",
          "name": "left",
          "persistentUuid": "5f077967-74c7-4821-a8a2-cad65480c12d",
          "width": 0,
          "x": 1280,
          "y": 528,
          "zOrder": 8,
          "numberProperties": [],
          "stringProperties": [],
          "initialVariables": []
        },
        {
          "angle": 0,
          "customSize": false,
          "height": 0,
          "layer": "",
          "name": "right",
          "persistentUuid": "309e59f7-ced4-4786-a803-45c8f506d8b8",
          "width": 0,
          "x": 540,
          "y": 524,
          "zOrder": 9,
          "numberProperties": [],
          "stringProperties": [],
          "initialVariables": []
        }
      ],
      "objects": [
        {
          "assetStoreId": "",
          "name": "Player",
          "tags": "",
          "type": "Sprite",
          "updateIfNotVisible": false,
          "variables": [],
          "effects": [],
          "behaviors": [
            {
              "name": "PlatformerObject",
              "type": "PlatformBehavior::PlatformerObjectBehavior",
              "acceleration": 1500,
              "canGoDownFromJumpthru": true,
              "canGrabPlatforms": false,
              "canGrabWithoutMoving": true,
              "deceleration": 1500,
              "gravity": 1000,
              "ignoreDefaultControls": false,
              "jumpSpeed": 600,
              "jumpSustainTime": 0.2,
              "ladderClimbingSpeed": 150,
              "maxFallingSpeed": 700,
              "maxSpeed": 250,
              "slopeMaxAngle": 60,
              "useLegacyTrajectory": false,
              "xGrabTolerance": 10,
              "yGrabOffset": 0
            }
          ],
          "animations": [
            {
              "name": "Idle",
              "useMultipleDirections": false,
              "directions": [
                {
                  "looping": false,
                  "timeBetweenFrames": 0.08,
                  "sprites": [
                    {
                      "hasCustomCollisionMask": false,
                      "image": "img/p1_stand.png",
                      "points": [],
                      "originPoint": {
                        "name": "origine",
                        "x": 0,
                        "y": 0
                      },
                      "centerPoint": {
                        "automatic": true,
                        "name": "centre",
                        "x": 0,
                        "y": 0
                      },
                      "customCollisionMask": []
                    }
                  ]
                }
              ]
            },
            {
              "name": "Jumping",
              "useMultipleDirections": false,
              "directions": [
                {
                  "looping": false,
                  "timeBetweenFrames": 0.08,
                  "sprites": [
                    {
                      "hasCustomCollisionMask": false,
                      "image": "img/p1_jump.png",
                      "points": [],
                      "originPoint": {
                        "name": "origine",
                        "x": 0,
                        "y": 0
                      },
                      "centerPoint": {
                        "automatic": true,
                        "name": "centre",
                        "x": 0,
                        "y": 0
                      },
                      "customCollisionMask": []
                    }
                  ]
                }
              ]
            },
            {
              "name": "Running",
              "useMultipleDirections": false,
              "directions": [
                {
                  "looping": true,
                  "timeBetweenFrames": 0.08,
                  "sprites": [
                    {
                      "hasCustomCollisionMask": false,
                      "image": "img/p1_walk03.png",
                      "points": [],
                      "originPoint": {
                        "name": "origine",
                        "x": 0,
                        "y": 0
                      },
                      "centerPoint": {
                        "automatic": true,
                        "name": "centre",
                        "x": 0,
                        "y": 0
                      },
                      "customCollisionMask": []
                    },
                    {
                      "hasCustomCollisionMask": false,
                      "image": "img/p1_walk04.png",
                      "points": [],
                      "originPoint": {
                        "name": "origine",
                        "x": 0,
                        "y": 0
                      },
                      "centerPoint": {
                        "automatic": true,
                        "name": "centre",
                        "x": 0,
                        "y": 0
                      },
                      "customCollisionMask": []
                    },
                    {
                      "hasCustomCollisionMask": false,
                      "image": "img/p1_walk05.png",
                      "points": [],
                      "originPoint": {
                        "name": "origine",
                        "x": 0,
                        "y": 0
                      },
                      "centerPoint": {
                        "automatic": true,
                        "name": "centre",
                        "x": 0,
                        "y": 0
                      },
                      "customCollisionMask": []
                    },
                    {
                      "hasCustomCollisionMask": false,
                      "image": "img/p1_walk06.png",
                      "points": [],
                      "originPoint": {
                        "name": "origine",
                        "x": 0,
                        "y": 0
                      },
                      "centerPoint": {
                        "automatic": true,
                        "name": "centre",
                        "x": 0,
                        "y": 0
                      },
                      "customCollisionMask": []
                    },
                    {
                      "hasCustomCollisionMask": false,
                      "image": "img/p1_walk07.png",
                      "points": [],
                      "originPoint": {
                        "name": "origine",
                        "x": 0,
                        "y": 0
                      },
                      "centerPoint": {
                        "automatic": true,
                        "name": "centre",
                        "x": 0,
                        "y": 0
                      },
                      "customCollisionMask": []
                    }
                  ]
                }
              ]
            }
          ]
        },
        {
          "assetStoreId": "",
          "height": 32,
          "name": "BottomGrassPlatform",
          "tags": "",
          "texture": "img/grassHalfMid.png",
          "type": "TiledSpriteObject::TiledSprite",
          "width": 32,
          "variables": [],
          "effects": [],
          "behaviors": [
            {
              "name": "Platform",
              "type": "PlatformBehavior::PlatformBehavior",
              "canBeGrabbed": false,
              "platformType": "NormalPlatform",
              "yGrabOffset": 0
            }
          ]
        },
        {
          "assetStoreId": "",
          "height": 32,
          "name": "GrassPlatform",
          "tags": "",
          "texture": "img/grassHalfMid.png",
          "type": "TiledSpriteObject::TiledSprite",
          "width": 32,
          "variables": [],
          "effects": [],
          "behaviors": [
            {
              "name": "Platform",
              "type": "PlatformBehavior::PlatformBehavior",
              "canBeGrabbed": false,
              "platformType": "NormalPlatform",
              "yGrabOffset": 0
            }
          ]
        },
        {
          "assetStoreId": "",
          "name": "SmallBridge",
          "tags": "",
          "type": "Sprite",
          "updateIfNotVisible": false,
          "variables": [],
          "effects": [],
          "behaviors": [
            {
              "name": "Platform",
              "type": "PlatformBehavior::PlatformBehavior",
              "canBeGrabbed": false,
              "platformType": "Jumpthru",
              "yGrabOffset": 0
            }
          ],
          "animations": [
            {
              "name": "",
              "useMultipleDirections": false,
              "directions": [
                {
                  "looping": false,
                  "timeBetweenFrames": 0.08,
                  "sprites": [
                    {
                      "hasCustomCollisionMask": false,
                      "image": "img/bridgeLogs.png",
                      "points": [],
                      "originPoint": {
                        "name": "origine",
                        "x": 0,
                        "y": 0
                      },
                      "centerPoint": {
                        "automatic": true,
                        "name": "centre",
                        "x": 0,
                        "y": 0
                      },
                      "customCollisionMask": []
                    }
                  ]
                }
              ]
            }
          ]
        },
        {
          "assetStoreId": "",
          "name": "Bush",
          "tags": "",
          "type": "Sprite",
          "updateIfNotVisible": false,
          "variables": [],
          "effects": [],
          "behaviors": [],
          "animations": [
            {
              "name": "",
              "useMultipleDirections": false,
              "directions": [
                {
                  "looping": false,
                  "timeBetweenFrames": 0.08,
                  "sprites": [
                    {
                      "hasCustomCollisionMask": false,
                      "image": "img/bush.png",
                      "points": [],
                      "originPoint": {
                        "name": "origine",
                        "x": 0,
                        "y": 0
                      },
                      "centerPoint": {
                        "automatic": true,
                        "name": "centre",
                        "x": 0,
                        "y": 0
                      },
                      "customCollisionMask": []
                    }
                  ]
                }
              ]
            }
          ]
        },
        {
          "assetStoreId": "",
          "name": "Cloud",
          "tags": "",
          "type": "Sprite",
          "updateIfNotVisible": false,
          "variables": [],
          "effects": [],
          "behaviors": [],
          "animations": [
            {
              "name": "",
              "useMultipleDirections": false,
              "directions": [
                {
                  "looping": false,
                  "timeBetweenFrames": 0.08,
                  "sprites": [
                    {
                      "hasCustomCollisionMask": false,
                      "image": "img/cloud2.png",
                      "points": [],
                      "originPoint": {
                        "name": "origine",
                        "x": 0,
                        "y": 0
                      },
                      "centerPoint": {
                        "automatic": true,
                        "name": "centre",
                        "x": 0,
                        "y": 0
                      },
                      "customCollisionMask": []
                    }
                  ]
                }
              ]
            }
          ]
        },
        {
          "assetStoreId": "",
          "name": "Coin",
          "tags": "",
          "type": "Sprite",
          "updateIfNotVisible": false,
          "variables": [],
          "effects": [],
          "behaviors": [],
          "animations": [
            {
              "name": "",
              "useMultipleDirections": false,
              "directions": [
                {
                  "looping": false,
                  "timeBetweenFrames": 0.08,
                  "sprites": [
                    {
                      "hasCustomCollisionMask": false,
                      "image": "img/coinGold.png",
                      "points": [],
                      "originPoint": {
                        "name": "origine",
                        "x": 0,
                        "y": 0
                      },
                      "centerPoint": {
                        "automatic": true,
                        "name": "centre",
                        "x": 0,
                        "y": 0
                      },
                      "customCollisionMask": []
                    }
                  ]
                }
              ]
            }
          ]
        },
        {
          "assetStoreId": "",
          "bold": false,
          "italic": false,
          "name": "Score",
          "smoothed": true,
          "tags": "",
          "type": "TextObject::Text",
          "underlined": false,
          "variables": [],
          "effects": [],
          "behaviors": [],
          "string": "Score :",
          "font": "fonts/Bimbo_JVE.ttf",
          "textAlignment": "left",
          "characterSize": 40,
          "color": {
            "b": 0,
            "g": 0,
            "r": 0
          }
        },
        {
          "assetStoreId": "",
          "name": "Slime",
          "tags": "",
          "type": "Sprite",
          "updateIfNotVisible": false,
          "variables": [
            {
              "folded": true,
              "name": "direction",
              "type": "string",
              "value": "left"
            }
          ],
          "effects": [],
          "behaviors": [],
          "animations": [
            {
              "name": "Walk",
              "useMultipleDirections": false,
              "directions": [
                {
                  "looping": true,
                  "timeBetweenFrames": 0.5,
                  "sprites": [
                    {
                      "hasCustomCollisionMask": false,
                      "image": "img/slimeWalk1.png",
                      "points": [],
                      "originPoint": {
                        "name": "origine",
                        "x": 0,
                        "y": 0
                      },
                      "centerPoint": {
                        "automatic": true,
                        "name": "centre",
                        "x": 0,
                        "y": 0
                      },
                      "customCollisionMask": []
                    },
                    {
                      "hasCustomCollisionMask": false,
                      "image": "img/slimeWalk2.png",
                      "points": [],
                      "originPoint": {
                        "name": "origine",
                        "x": 0,
                        "y": 0
                      },
                      "centerPoint": {
                        "automatic": true,
                        "name": "centre",
                        "x": 0,
                        "y": 0
                      },
                      "customCollisionMask": []
                    }
                  ]
                }
              ]
            }
          ]
        },
        {
          "assetStoreId": "",
          "name": "left",
          "tags": "",
          "type": "Sprite",
          "updateIfNotVisible": false,
          "variables": [],
          "effects": [],
          "behaviors": [],
          "animations": [
            {
              "name": "",
              "useMultipleDirections": false,
              "directions": [
                {
                  "looping": false,
                  "timeBetweenFrames": 0.08,
                  "sprites": [
                    {
                      "hasCustomCollisionMask": false,
                      "image": "img/Left.png",
                      "points": [],
                      "originPoint": {
                        "name": "origine",
                        "x": 0,
                        "y": 0
                      },
                      "centerPoint": {
                        "automatic": true,
                        "name": "centre",
                        "x": 0,
                        "y": 0
                      },
                      "customCollisionMask": []
                    }
                  ]
                }
              ]
            }
          ]
        },
        {
          "assetStoreId": "",
          "name": "right",
          "tags": "",
          "type": "Sprite",
          "updateIfNotVisible": false,
          "variables": [],
          "effects": [],
          "behaviors": [],
          "animations": [
            {
              "name": "",
              "useMultipleDirections": false,
              "directions": [
                {
                  "looping": false,
                  "timeBetweenFrames": 0.08,
                  "sprites": [
                    {
                      "hasCustomCollisionMask": false,
                      "image": "img/Right.png",
                      "points": [],
                      "originPoint": {
                        "name": "origine",
                        "x": 0,
                        "y": 0
                      },
                      "centerPoint": {
                        "automatic": true,
                        "name": "centre",
                        "x": 0,
                        "y": 0
                      },
                      "customCollisionMask": []
                    }
                  ]
                }
              ]
            }
          ]
        }
      ],
      "events": [
        {
          "type": "BuiltinCommonInstructions::Standard",
          "conditions": [
            {
              "type": {
                "value": "PlatformBehavior::IsJumping"
              },
              "parameters": [
                "Player",
                "PlatformerObject"
              ]
            }
          ],
          "actions": [
            {
              "type": {
                "value": "SetAnimationName"
              },
              "parameters": [
                "Player",
                "\"Jumping\""
              ]
            }
          ]
        },
        {
          "type": "BuiltinCommonInstructions::Standard",
          "conditions": [
            {
              "type": {
                "value": "PlatformBehavior::IsFalling"
              },
              "parameters": [
                "Player",
                "PlatformerObject"
              ]
            }
          ],
          "actions": [
            {
              "type": {
                "value": "SetAnimationName"
              },
              "parameters": [
                "Player",
                "\"Jumping\""
              ]
            }
          ]
        },
        {
          "type": "BuiltinCommonInstructions::Standard",
          "conditions": [
            {
              "type": {
                "value": "PlatformBehavior::IsOnFloor"
              },
              "parameters": [
                "Player",
                "PlatformerObject"
              ]
            }
          ],
          "actions": [],
          "events": [
            {
              "type": "BuiltinCommonInstructions::Standard",
              "conditions": [
                {
                  "type": {
                    "value": "PlatformBehavior::PlatformerObjectBehavior::IsMovingEvenALittle"
                  },
                  "parameters": [
                    "Player",
                    "PlatformerObject"
                  ]
                }
              ],
              "actions": [
                {
                  "type": {
                    "value": "SetAnimationName"
                  },
                  "parameters": [
                    "Player",
                    "\"Running\""
                  ]
                }
              ]
            },
            {
              "type": "BuiltinCommonInstructions::Standard",
              "conditions": [
                {
                  "type": {
                    "inverted": true,
                    "value": "PlatformBehavior::PlatformerObjectBehavior::IsMovingEvenALittle"
                  },
                  "parameters": [
                    "Player",
                    "PlatformerObject"
                  ]
                }
              ],
              "actions": [
                {
                  "type": {
                    "value": "SetAnimationName"
                  },
                  "parameters": [
                    "Player",
                    "\"Idle\""
                  ]
                }
              ]
            }
          ]
        },
        {
          "type": "BuiltinCommonInstructions::Standard",
          "conditions": [],
          "actions": [
            {
              "type": {
                "value": "CentreCamera"
              },
              "parameters": [
                "",
                "Player",
                "",
                "",
                ""
              ]
            }
          ]
        },
        {
          "type": "BuiltinCommonInstructions::Standard",
          "conditions": [
            {
              "type": {
                "value": "CollisionNP"
              },
              "parameters": [
                "Player",
                "Coin",
                "",
                "",
                ""
              ]
            }
          ],
          "actions": [
            {
              "type": {
                "value": "Delete"
              },
              "parameters": [
                "Coin",
                ""
              ]
            },
            {
              "type": {
                "value": "PlaySound"
              },
              "parameters": [
                "",
                "sounds/coin.mp3",
                "",
                "",
                ""
              ]
            },
            {
              "type": {
                "value": "ModVarScene"
              },
              "parameters": [
                "Score",
                "+",
                "100"
              ]
            },
            {
              "type": {
                "value": "TextObject::String"
              },
              "parameters": [
                "Score",
                "=",
                "\"Score : \" + ToString(Variable(Score))"
              ]
            }
          ]
        },
        {
          "type": "BuiltinCommonInstructions::Standard",
          "conditions": [
            {
              "type": {
                "value": "DepartScene"
              },
              "parameters": [
                ""
              ]
            }
          ],
          "actions": [
            {
              "type": {
                "value": "Cache"
              },
              "parameters": [
                "left"
              ]
            },
            {
              "type": {
                "value": "Cache"
              },
              "parameters": [
                "right"
              ]
            }
          ]
        },
        {
          "type": "BuiltinCommonInstructions::Standard",
          "conditions": [
            {
              "type": {
                "value": "CollisionNP"
              },
              "parameters": [
                "Slime",
                "right",
                "",
                "",
                ""
              ]
            }
          ],
          "actions": [
            {
              "type": {
                "value": "ModVarObjetTxt"
              },
              "parameters": [
                "Slime",
                "direction",
                "=",
                "\"right\""
              ]
            }
          ]
        },
        {
          "type": "BuiltinCommonInstructions::Standard",
          "conditions": [
            {
              "type": {
                "value": "CollisionNP"
              },
              "parameters": [
                "Slime",
                "left",
                "",
                "",
                ""
              ]
            }
          ],
          "actions": [
            {
              "type": {
                "value": "ModVarObjetTxt"
              },
              "parameters": [
                "Slime",
                "direction",
                "=",
                "\"left\""
              ]
            }
          ]
        },
        {
          "type": "BuiltinCommonInstructions::Standard",
          "conditions": [
            {
              "type": {
                "value": "VarObjetTxt"
              },
              "parameters": [
                "Slime",
                "direction",
                "=",
                "\"left\""
              ]
            }
          ],
          "actions": [
            {
              "type": {
                "value": "AddForceAL"
              },
              "parameters": [
                "Slime",
                "180",
                "100",
                ""
              ]
            },
            {
              "type": {
                "value": "FlipX"
              },
              "parameters": [
                "Slime",
                "no"
              ]
            }
          ]
        },
        {
          "type": "BuiltinCommonInstructions::Standard",
          "conditions": [
            {
              "type": {
                "value": "VarObjetTxt"
              },
              "parameters": [
                "Slime",
                "direction",
                "=",
                "\"right\""
              ]
            }
          ],
          "actions": [
            {
              "type": {
                "value": "AddForceAL"
              },
              "parameters": [
                "Slime",
                "0",
                "100",
                ""
              ]
            },
            {
              "type": {
                "value": "FlipX"
              },
              "parameters": [
                "Slime",
                "yes"
              ]
            }
          ]
        },
        {
          "type": "BuiltinCommonInstructions::Standard",
          "conditions": [
            {
              "type": {
                "value": "CollisionNP"
              },
              "parameters": [
                "Player",
                "Slime",
                "",
                "",
                ""
              ]
            },
            {
              "type": {
                "value": "PlatformBehavior::IsOnFloor"
              },
              "parameters": [
                "Player",
                "PlatformerObject"
              ]
            }
          ],
          "actions": [
            {
              "type": {
                "value": "Delete"
              },
              "parameters": [
                "Player",
                ""
              ]
            }
          ]
        },
        {
          "type": "BuiltinCommonInstructions::Standard",
          "conditions": [
            {
              "type": {
                "value": "CollisionNP"
              },
              "parameters": [
                "Player",
                "Slime",
                "",
                "",
                ""
              ]
            },
            {
              "type": {
                "value": "PlatformBehavior::IsFalling"
              },
              "parameters": [
                "Player",
                "PlatformerObject"
              ]
            }
          ],
          "actions": [
            {
              "type": {
                "value": "Delete"
              },
              "parameters": [
                "Slime",
                ""
              ]
            },
            {
              "type": {
                "value": "PlatformBehavior::SetCanJump"
              },
              "parameters": [
                "Player",
                "PlatformerObject"
              ]
            },
            {
              "type": {
                "value": "PlatformBehavior::SimulateJumpKey"
              },
              "parameters": [
                "Player",
                "PlatformerObject"
              ]
            }
          ]
        }
      ],
      "layers": [
        {
          "ambientLightColorB": 0,
          "ambientLightColorG": 8042920,
          "ambientLightColorR": 16,
          "followBaseLayerCamera": false,
          "isLightingLayer": false,
          "name": "",
          "visibility": true,
          "cameras": [
            {
              "defaultSize": true,
              "defaultViewport": true,
              "height": 0,
              "viewportBottom": 1,
              "viewportLeft": 0,
              "viewportRight": 1,
              "viewportTop": 0,
              "width": 0
            }
          ],
          "effects": []
        },
        {
          "ambientLightColorB": 7723384,
          "ambientLightColorG": 6059824,
          "ambientLightColorR": 7420608,
          "followBaseLayerCamera": false,
          "isLightingLayer": false,
          "name": "UI",
          "visibility": true,
          "cameras": [],
          "effects": []
        }
      ],
      "behaviorsSharedData": [
        {
          "name": "Platform",
          "type": "PlatformBehavior::PlatformBehavior"
        },
        {
          "name": "PlatformerObject",
          "type": "PlatformBehavior::PlatformerObjectBehavior"
        }
      ]
    }
  ],
  "externalEvents": [],
  "eventsFunctionsExtensions": [],
  "externalLayouts": [],
  "externalSourceFiles": []
}